mcp_weather_http/__init__.py
mcp_weather_http/__main__.py
mcp_weather_http/server.py
weatherinfohttpstreammcpserver-0.1.0.dist-info/METADATA
weatherinfohttpstreammcpserver-0.1.0.dist-info/WHEEL
weatherinfohttpstreammcpserver-0.1.0.dist-info/entry_points.txt
weatherinfohttpstreammcpserver-0.1.0.dist-info/top_level.txt
weatherinfohttpstreammcpserver-0.1.0.dist-info/RECORD
